python_vitrageclient-5.3.0.data/data/share/vitrage.bash_completion
vitrageclient/__init__.py
vitrageclient/auth.py
vitrageclient/client.py
vitrageclient/exceptions.py
vitrageclient/osc.py
vitrageclient/shell.py
vitrageclient/common/__init__.py
vitrageclient/common/formatters.py
vitrageclient/common/utils.py
vitrageclient/common/yaml_utils.py
vitrageclient/tests/__init__.py
vitrageclient/tests/test_template.py
vitrageclient/tests/utils.py
vitrageclient/tests/cli/__init__.py
vitrageclient/tests/cli/base.py
vitrageclient/tests/cli/test_event_post.py
vitrageclient/tests/cli/test_topology_show.py
vitrageclient/tests/resources/template1.yaml
vitrageclient/v1/__init__.py
vitrageclient/v1/alarm.py
vitrageclient/v1/client.py
vitrageclient/v1/event.py
vitrageclient/v1/healthcheck.py
vitrageclient/v1/rca.py
vitrageclient/v1/resource.py
vitrageclient/v1/service.py
vitrageclient/v1/status.py
vitrageclient/v1/template.py
vitrageclient/v1/topology.py
vitrageclient/v1/webhook.py
vitrageclient/v1/cli/__init__.py
vitrageclient/v1/cli/alarm.py
vitrageclient/v1/cli/event.py
vitrageclient/v1/cli/healthcheck.py
vitrageclient/v1/cli/rca.py
vitrageclient/v1/cli/resource.py
vitrageclient/v1/cli/service.py
vitrageclient/v1/cli/status.py
vitrageclient/v1/cli/template.py
vitrageclient/v1/cli/topology.py
vitrageclient/v1/cli/webhook.py
python_vitrageclient-5.3.0.dist-info/AUTHORS
python_vitrageclient-5.3.0.dist-info/LICENSE
python_vitrageclient-5.3.0.dist-info/METADATA
python_vitrageclient-5.3.0.dist-info/WHEEL
python_vitrageclient-5.3.0.dist-info/entry_points.txt
python_vitrageclient-5.3.0.dist-info/pbr.json
python_vitrageclient-5.3.0.dist-info/top_level.txt
python_vitrageclient-5.3.0.dist-info/RECORD
