Metadata-Version: 2.1
Name: python-vitrageclient
Version: 5.3.0
Summary: Vitrage Client API Library
Home-page: https://docs.openstack.org/python-vitrageclient/latest/
Author: OpenStack
Author-email: openstack-discuss@lists.openstack.org
Classifier: Environment :: OpenStack
Classifier: Intended Audience :: Information Technology
Classifier: Intended Audience :: System Administrators
Classifier: License :: OSI Approved :: Apache Software License
Classifier: Operating System :: POSIX :: Linux
Classifier: Programming Language :: Python
Classifier: Programming Language :: Python :: Implementation :: CPython
Classifier: Programming Language :: Python :: 3 :: Only
Classifier: Programming Language :: Python :: 3
Classifier: Programming Language :: Python :: 3.8
Classifier: Programming Language :: Python :: 3.9
Classifier: Programming Language :: Python :: 3.10
Classifier: Programming Language :: Python :: 3.11
Requires-Python: >=3.8
License-File: LICENSE
License-File: AUTHORS
Requires-Dist: pbr >=3.1.1
Requires-Dist: cliff !=2.9.0,>=2.8.0
Requires-Dist: osc-lib >=1.8.0
Requires-Dist: oslo.utils >=3.33.0
Requires-Dist: keystoneauth1 >=3.4.0
Requires-Dist: iso8601 >=0.1.11
Requires-Dist: networkx >=2.3
Requires-Dist: pydot >=1.4.1
Requires-Dist: oslo.log >=4.4.0
